{"version":1,"resource":"file:///Users/jackpeck/Documents/dev/twin/media-center/backend/handlers/PrHandler.go","entries":[{"id":"ZxF6.go","timestamp":1652606574769},{"id":"XkxE.go","timestamp":1652606644943},{"id":"S6Ia.go","timestamp":1652618723914},{"id":"AAfL.go","timestamp":1652618827986},{"id":"QLRF.go","timestamp":1652619004738},{"id":"uLA5.go","timestamp":1652619119913},{"id":"8IS2.go","timestamp":1652619139771},{"id":"AHsG.go","timestamp":1652619273700},{"id":"oka3.go","timestamp":1652619360187},{"id":"aEa0.go","timestamp":1652619421563},{"id":"AJ5W.go","timestamp":1652686653305},{"id":"JvMC.go","source":"undoRedo.source","timestamp":1652689486714}]}